admintool_command/__init__.py
admintool_command/command.py
admintool_command/dashboards.py
admintool_command/models.py
admintool_command/urls.py
admintool_command/utils.py
admintool_command/views.py
admintool_command/templates/admintool_command/command.html
admintool_command/templatetags/__init__.py
admintool_command/templatetags/admintool_command_tags.py
admintool_command/tests/__init__.py
admintool_command/tests/models_tests.py
admintool_command/tests/settings.py
admintool_command/tests/test_settings.py
admintool_command/tests/urls.py
admintool_command/tests/test_app/__init__.py
admintool_command/tests/test_app/models.py
admintool_command/tests/test_app/templates/400.html
admintool_command/tests/test_app/templates/500.html
django_admintool_command-0.1.1.dist-info/AUTHORS
django_admintool_command-0.1.1.dist-info/LICENSE
django_admintool_command-0.1.1.dist-info/METADATA
django_admintool_command-0.1.1.dist-info/WHEEL
django_admintool_command-0.1.1.dist-info/top_level.txt
django_admintool_command-0.1.1.dist-info/RECORD
